explipy/__init__.py
explipy/core.py
explipy/parser.py
explipy/rules.py
explipy/utils.py
explipy-0.1.2.dist-info/METADATA
explipy-0.1.2.dist-info/WHEEL
explipy-0.1.2.dist-info/top_level.txt
explipy-0.1.2.dist-info/RECORD
