Metadata-Version: 2.4
Name: explipy
Version: 0.1.2
Summary: Human-readable exception explanations for Python, including NumPy, Pandas, and requests.
Author-email: veliqq <veliqorg@proton.me>
License: MIT
Project-URL: Homepage, https://github.com/veliqq/explipy
Project-URL: Repository, https://github.com/veliqq/explipy
Project-URL: Documentation, https://github.com/veliqq/explipy#readme
Keywords: python,exceptions,traceback,debugging,error,numpy,pandas,requests
Classifier: Programming Language :: Python :: 3
Classifier: License :: OSI Approved :: MIT License
Classifier: Operating System :: OS Independent
Classifier: Development Status :: 4 - Beta
Classifier: Intended Audience :: Developers
Classifier: Topic :: Software Development :: Debuggers
Requires-Python: >=3.8
Provides-Extra: dev
Requires-Dist: pytest>=7.0; extra == "dev"
Requires-Dist: black; extra == "dev"
Requires-Dist: isort; extra == "dev"
